rlds/__init__.py
rlds/rlds_types.py
rlds/rlds_types_test.py
rlds/metadata/__init__.py
rlds/metadata/metadata_types.py
rlds/tfds/__init__.py
rlds/tfds/config_generator.py
rlds/tfds/config_generator_test.py
rlds/tfds/episode_writer.py
rlds/transformations/__init__.py
rlds/transformations/alignment.py
rlds/transformations/alignment_test.py
rlds/transformations/batched_helpers.py
rlds/transformations/batched_helpers_test.py
rlds/transformations/dataset_concat.py
rlds/transformations/dataset_concat_test.py
rlds/transformations/dataset_stats.py
rlds/transformations/dataset_stats_test.py
rlds/transformations/dataset_truncate.py
rlds/transformations/dataset_truncate_test.py
rlds/transformations/flexible_batch.py
rlds/transformations/flexible_batch_test.py
rlds/transformations/nested_ops.py
rlds/transformations/nested_ops_test.py
rlds/transformations/pattern.py
rlds/transformations/pattern_test.py
rlds/transformations/shape_ops.py
rlds/transformations/shape_ops_test.py
rlds/transformations/transformations_testlib.py
rlds-0.1.8.dist-info/LICENSE
rlds-0.1.8.dist-info/METADATA
rlds-0.1.8.dist-info/WHEEL
rlds-0.1.8.dist-info/top_level.txt
rlds-0.1.8.dist-info/RECORD
